{
  "projects": [
    {
      "name": "Projeto Python",
      "budget": "15000",
      "category": {
        "id": "4",
        "name": "Planejamento"
      },
      "cost": 0,
      "services": [],
      "id": 1
    },
    {
      "name": "Projeto Java",
      "budget": "7000",
      "category": {
        "id": "2",
        "name": "Desenvolvimento"
      },
      "cost": 100,
      "services": [
        {
          "name": "Programador Java",
          "cost": "100",
          "description": "Contratação de um Freelancer Java",
          "id": "fcb52db0-2947-4e40-8c3d-66aba3954264"
        }
      ],
      "id": 2
    }
  ],
  "categories": [
    {
      "id": 1,
      "name": "Infra"
    },
    {
      "id": 2,
      "name": "Desenvolvimento"
    },
    {
      "id": 3,
      "name": "Design"
    },
    {
      "id": 4,
      "name": "Planejamento"
    }
  ]
}